drop_analysis/FrameSupply.py
drop_analysis/Mainwindow.ui
drop_analysis/Settings.ui
drop_analysis/__init__.py
drop_analysis/__main__.py
drop_analysis/config.toml
drop_analysis/edge_analysis.py
drop_analysis/edge_detection.py
drop_analysis/gui.py
drop_analysis/otsu.py
drop_analysis/settings.py
drop_analysis/version.py
drop_analysis/data/README.rst
drop_analysis/data/__init__.py
drop_analysis/data/common_resolutions.csv
drop_analysis/data/icon.ico
drop_analysis/data/icon.xcf
drop_analysis/tests/__init__.py
drop_analysis-0.3.0b0.dist-info/LICENSE
drop_analysis-0.3.0b0.dist-info/METADATA
drop_analysis-0.3.0b0.dist-info/WHEEL
drop_analysis-0.3.0b0.dist-info/entry_points.txt
drop_analysis-0.3.0b0.dist-info/top_level.txt
drop_analysis-0.3.0b0.dist-info/RECORD
