Metadata-Version: 2.1
Name: drop-analysis
Version: 0.3.0b0
Summary: A program to capture and analyze images of droplets
Home-page: https://github.com/mvgorcum/Sessile.drop.analysis
Author: Mathijs van Gorcum
Author-email: mathijs@vgorcum.com
License: GNU GPL v3+
Platform: UNKNOWN
Requires-Python: >=3.8
License-File: LICENSE
Requires-Dist: numpy
Requires-Dist: pandas
Requires-Dist: scipy
Requires-Dist: pyqt5
Requires-Dist: opencv-python-headless
Requires-Dist: openpyxl
Requires-Dist: fast-histogram
Requires-Dist: lsq-ellipse
Requires-Dist: imageio
Requires-Dist: shapely
Requires-Dist: pyqtgraph (>=0.11.0)
Requires-Dist: toml
Requires-Dist: h5py
Requires-Dist: appdirs
Provides-Extra: test
Requires-Dist: pytest ; extra == 'test'
